lektor_brunch_support.py
lektor_brunch_support-0.1.1.dist-info/DESCRIPTION.rst
lektor_brunch_support-0.1.1.dist-info/METADATA
lektor_brunch_support-0.1.1.dist-info/RECORD
lektor_brunch_support-0.1.1.dist-info/WHEEL
lektor_brunch_support-0.1.1.dist-info/entry_points.txt
lektor_brunch_support-0.1.1.dist-info/metadata.json
lektor_brunch_support-0.1.1.dist-info/top_level.txt
