Metadata-Version: 2.0
Name: lektor-brunch-support
Version: 0.1.1
Summary: Adds support for Brunch to Lektor.
Home-page: http://github.com/SShrike/lektor-brunch-support
Author: Severen Redwood
Author-email: severen@shrike.me
License: MPL-2.0
Keywords: lektor plugin
Platform: UNKNOWN
Classifier: Development Status :: 4 - Beta
Classifier: Intended Audience :: Developers
Classifier: License :: OSI Approved :: Mozilla Public License 2.0 (MPL 2.0)
Classifier: Programming Language :: Python :: 2
Classifier: Programming Language :: Python :: 2.7
Classifier: Programming Language :: Python :: 3
Classifier: Programming Language :: Python :: 3.4
Classifier: Programming Language :: Python :: 3.5
